pytest_gitlab/__init__.py
pytest_gitlab/__version__.py
pytest_gitlab/plugin.py
pytest_gitlab/docker/.env
pytest_gitlab/docker/__init__.py
pytest_gitlab/docker/avatar.png
pytest_gitlab/docker/create_license.rb
pytest_gitlab/docker/docker-compose.yml
pytest_gitlab/docker/docker.py
pytest_gitlab/docker/install_docker.sh
pytest_gitlab/docker/invalid_auth.cfg
pytest_gitlab/docker/invalid_version.cfg
pytest_gitlab/docker/set_token.rb
pytest_gitlab/fixtures/__init__.py
pytest_gitlab/fixtures/gitlab.py
pytest_gitlab/fixtures/helpers.py
pytest_gitlab/fixtures/meta.py
pytest_gitlab-0.3.1.dist-info/METADATA
pytest_gitlab-0.3.1.dist-info/WHEEL
pytest_gitlab-0.3.1.dist-info/entry_points.txt
pytest_gitlab-0.3.1.dist-info/licenses/COPYING
pytest_gitlab-0.3.1.dist-info/RECORD
