Metadata-Version: 2.3
Name: pytest-gitlab
Version: 0.3.1
Summary: Pytest Plugin for Gitlab
Author-email: Thomas Hartmann <thomas.hartmann@th-ht.de>
License-File: COPYING
Requires-Python: >=3.9
Requires-Dist: attrs
Requires-Dist: pytest-docker
Requires-Dist: python-gitlab
